setup.py
bachata/__init__.py
bachata/base.py
bachata/proto.py
bachata/redis.py
bachata/routes.py
bachata/tests.py
bachata/tornado.py
bachata.egg-info/PKG-INFO
bachata.egg-info/SOURCES.txt
bachata.egg-info/dependency_links.txt
bachata.egg-info/not-zip-safe
bachata.egg-info/requires.txt
bachata.egg-info/top_level.txt