Metadata-Version: 1.1
Name: bachata
Version: 0.1
Summary: Bachata is a chat server toolkit on top of asyncio and Tornado.
Home-page: https://github.com/05bit/bachata
Author: Alexey Kinev
Author-email: rudy@05bit.com
License: Apache
Platform: UNKNOWN
Classifier: Development Status :: 3 - Alpha
Classifier: Environment :: Web Environment
Classifier: Intended Audience :: Developers
Classifier: License :: OSI Approved :: Apache Software License
Classifier: Programming Language :: Python :: 3
